{"booleanBadAnswer":"1","questions":[{"libelleQuestion":"Q1 facile","reponseFausse":["Q1RF1","Q1RF2","Q1RF3","Q1RF4"],"difficulte":"Facile","reponseVraie":"Q1RC1"},{"libelleQuestion":"question facileg","reponseFausse":["b","c","d","e"],"difficulte":"Facile","reponseVraie":"a"},{"libelleQuestion":"question moyen","reponseFausse":["eta","tea","te","t"],"difficulte":"Moyen","reponseVraie":"lal"},{"libelleQuestion":"Quel est mon prenom ?","reponseFausse":["Nono","Tito","Antoine","Nina"],"difficulte":"Facile","reponseVraie":"Nino"},{"libelleQuestion":"bonjour \"?","reponseFausse":["rep F","rep F2","rep F3","rep 4"],"difficulte":"Facile","reponseVraie":"reP C"},{"libelleQuestion":"question 3","reponseFausse":["rep F","rep F2","rep F3","rep 4"],"difficulte":"Facile","reponseVraie":"reP C\""}]}